{
    "menu:npc_mugging": "<i class=\"bi bi-wallet\"></i> Okradanie NPC",
    "menu:cargo_robbery": "<i class=\"bi bi-truck\"></i> Okradanie Ciężarówki",
    "menu:heist_tab": "<i class=\"bi bi-bank\"></i> Napad",
    "menu:settings": "<i class=\"bi bi-gear-fill\"></i> Ustawnienia",
    "menu:can_make_npc_to_follow": "Możesz sprawdzic że NPC będzie podążał za tobą",
    "menu:time_to_mug": "Czas do obrabowania NPC (sekundy)",
    "menu:minutes_before_automatically_run_away": "Kilka minut przed automatyczną ucieczką",
    "menu:robbable_items": "Przedmioty do okradzenia",
    "menu:add_object": "Dodaj objekt",
    "menu:item": "Itemy",
    "menu:account": "Konto",
    "menu:weapon": "Broń",
    "menu:min_quantity": "Minimalna ilość",
    "menu:max_quantity": "Maksymalna ilość",
    "menu:probability": "Prawdopodobieństwo",
    "menu:choose": "Wybierz",
    "menu:police": "Policja",
    "menu:minimum_police": "Minimalna ilość policji na służbie",
    "menu:alert_police_chances": "Prawdopodobieństwo, że policja zostanie zaalarmowana",
    "menu:amount_of_objects_can_give": "Ilość przedmiotów, które NPC może dać",
    "menu:new_heist": "Nowy napad",
    "menu:id": "ID",
    "menu:settings:language": "Język",
    "menu:required_for_cargo_robbery": "Item do napadu na ciężarówke",
    "menu:label": "Label",
    "menu:x": "X",
    "menu:y": "Y",
    "menu:z": "Z",
    "menu:heist": "Napad",
    "menu:delete": "Usuń",
    "menu:close": "Zamknij",
    "menu:create": "Stwórz",
    "menu:generic": "Ogólny",
    "menu:marker_customization": "Personalizacja markera",
    "menu:confirm": "Akceptuj",
    "menu:marker_size": "Wielkość markera",
    "menu:marker_rotation": "Obrót markera",
    "menu:marker_color": "Kolor markera",
    "menu:red": "Czerwony",
    "menu:green": "Zielony",
    "menu:blue": "Niebieski",
    "menu:opacity": "Nieprzezroczystość",
    "menu:other": "Reszta",
    "menu:bounce": "Bounce",
    "menu:follow_camera": "Śledź kamerę",
    "menu:rotate": "Obracanie",
    "menu:marker_type": "Typ markera",
    "menu:add_stage": "Dodaj etap",
    "menu:stages": "Etapy",
    "menu:stage": "Etap",
    "menu:heading": "Wysokość",
    "menu:blip_customization": "Personalizacja Blipa",
    "menu:blip_sprite": "Blip sprite",
    "menu:blip_name": "Nazwa Blipa",
    "menu:blip_scale": "Skala blipa",
    "menu:blip_color": "Kolor blipa",
    "menu:blip_enabled": "Włączenie blipa",
    "menu:blip_display": "Wyświetlanie blipa",
    "menu:main_and_minimap": "Główna i minimapa",
    "menu:minimap_only": "Tylko minimapa",
    "menu:cash_1": "Gotówka 1",
    "menu:cash_2": "Gotówka 2",
    "menu:cash_3": "Gotówka 3",
    "menu:gold_1": "Złoto 1",
    "menu:gold_2": "Złoto 2",
    "menu:gold_3": "Złoto 3",
    "menu:diamond_1": "Diamenty 1",
    "menu:diamond_2": "Diamenty 2",
    "menu:current_coords_and_heading": "Aktualne współrzędne i wysokość",
    "menu:object_name": "Nazwa objektu",
    "menu:save": "Zapisz",
    "menu:add_robbable_object": "Dodaj obiekt do zrabowania",
    "menu:add_safe": "Dodaj sejf",
    "menu:safe_little": "Mały sejf",
    "menu:safe_big": "Duży sejf",
    "menu:add_item": "Dodaj item",
    "menu:difficulty": "Trudność",
    "menu:amount_of_objects_from_the_safe": "Ilość przedmiotów z sejfu",
    "menu:place_object": "Umieść obiekt",
    "menu:delete_stage": "Usuń etap",
    "menu:steps": "kroki",
    "menu:add_step": "Dodaj krok",
    "menu:is_optional": "Jest opcjonalny",
    "menu:heists_dialog:title": "Lista napadów",
    "menu:heists_dialog:search_heist": "Szukaj napadu",
    "menu:add_hackable_panel": "Dodaj panel do hakowania",
    "menu:robbable_object": "Przedmiot do okradzenia",
    "menu:safe": "Sejf",
    "menu:hackable_panel": "Panel do hakowania",
    "menu:is_invisible": "jest niewidoczny",
    "menu:add_thermal_charge": "Dodaj ładunek termiczny",
    "menu:thermal_charge": "ładunek termiczny",
    "menu:duration": "Czas trwania (sekundy)",
    "menu:requires_an_item": "Wymaga przedmiotu",
    "menu:lose_on_use": "Strać po użyciu",
    "menu:item_name": "Nazwa itemu",
    "menu:quantity": "Ilość",
    "menu:setup_alarms": "Ustaw alarm",
    "menu:alarms_dialog:title": "Lista alarmu",
    "menu:new_alarm": "Nowy alarm",
    "menu:police_and_alarm_bell": "Policja i dzwonek alarmowy",
    "menu:police_only": "Tylko policja",
    "menu:alarm_bell_only": "Tylko dzwonek alarmowy",
    "menu:add_lockpickable_door": "Dodaj drzwi do otwierania zamków",
    "menu:lockpickable_door": "Drzwi zamykane na zamek",
    "menu:add_lethal_gas": "Dodaj śmiertelny gaz",
    "menu:lethal_gas": "Śmiertelny gaz",
    "menu:place_gas_points": "Umieść punkty gazowe",
    "menu:damage": "Damage",
    "menu:color": "Kolor",
    "menu:second_to_wait": "Sekundy oczekiwania",
    "menu:second_to_wait_after_stage_start": "Sekundy oczekiwania po rozpoczęciu etapu",
    "menu:gas_color": "Kolor gazu, będzie DUŻO ciemniejszy niż wybrany",
    "menu:gas_mask": "Maska gazowa",
    "menu:mask_id": "ID Maski",
    "menu:minutes_timeout": "Limit minut",
    "menu:minutes_before_the_heist_can_be_done_again": "Kilka minut przed ponownym napadem",
    "menu:minutes_reset": "Minuty przed resetem",
    "menu:minutes_before_the_heist_will_reset": "Minuty przed zresetowaniem napadu po jego rozpoczęciu (kasowanie obiektów, resetowanie sceny, blokada drzwi itp.)",
    "menu:time_limit": "Limit czasu (minuty)",
    "menu:time_limit_description": "Minuty po rozpoczęciu napadu, kiedy użycie wszystkich obiektów zostanie wyłączone (nie usunięte). 0 bez limitu czasu",
    "menu:planning": "Planowanie",
    "menu:robberies": "Napady",
    "menu:new_cargo_robbery": "Nowy napad na ładunek",
    "menu:cargo_robbery_label": "Napad na ładunek",
    "menu:stops": "Przystanki",
    "menu:add_stop": "Dodaj przystanki",
    "menu:destination": "Miejsce docelowe",
    "menu:minutes_to_wait_when_arrived": "Minuty oczekiwania po przyjeździe",
    "menu:delete_stop": "Usuń przystanek",
    "menu:stop": "Zatrzymaj się",
    "menu:current_coords": "Aktualne współrzędne",
    "menu:can_always_carry_items": "Zawsze może nosić przedmioty",
    "menu:can_receive_multiple_times_the_same_item": "Może otrzymać wiele razy ten sam przedmiot",
    "menu:new_planning": "Nowe planowanie",
    "menu:cargo_robbery_name": "Nazwa napadu na ładunek",
    "menu:target_robbery": "Napad na cel",
    "menu:choose_robbery": "Wybierz rabunek",
    "menu:cargo_robberies_dialog:title": "Lista napadów na ładunki",
    "menu:cargo_robberies_dialog:search_heist": "Wyszukaj napad",
    "menu:none": "Nic",
    "menu:vehicle_model": "Model samochodu",
    "menu:driver_model": "Model kirowcy",
    "menu:armored_truck": "Ciężarówka opancerzona",
    "menu:max_speed": "Maksymalna prędkość",
    "menu:bulletproof_wheels": "Kuloodporne koła",
    "menu:drill": "Wiertło",
    "menu:time_to_drill": "Czas na wiercenie (sekundy)",
    "menu:menu:required_for_cargo_robbery": "Wymagane do napadu na ładunek",
    "menu:rewards": "Nagrody",
    "menu:amount_of_objects": "Ilość obiektów",
    "menu:rewards_list": "Lista nagród",
    "menu:deleting_minutes_after_rob": "Usuwanie minut po rabunku",
    "menu:after_robbed_description": "Minuty, które muszą upłynąć, zanim pojazd zostanie usunięty po jego kradzieży",
    "menu:deleting_minutes_after_destination": "Usuwanie minut po miejscu docelowym",
    "menu:after_final_destination_description": "Minuty, które muszą upłynąć, zanim pojazd zostanie usunięty po dotarciu do miejsca docelowego",
    "menu:max_minutes_difference_from_defined_date": "Maksymalna różnica minut od określonej daty",
    "menu:max_minutes_difference_from_defined_date_description": "Jeśli planowana data będzie starsza niż te minuty, zostanie usunięta (przykład: serwer zamknięty)",
    "menu:used_in_items_list": "Używane w wykazie przedmiotów (sejfy, napady na ładunek itp.)",
    "menu:now": "Teraz",
    "menu:date": "Data",
    "menu:interval": "Interwał",
    "menu:each": "Każdy",
    "menu:minutes": "Minuty",
    "menu:remaining_minutes": "Pozostałe minuty",
    "menu:requires_doors_creator": "Wymaga Kreatora Drzwi",
    "menu:main_webhook_description": "Domyślnie wszystkie logi zostaną umieszczone w tym webhooku, chyba że mają oddzielny webhook",
    "menu:npc_mugging_label": "Napad NPC",
    "menu:drive_randomly": "Jedź losowo",
    "menu:minutes_before_despawn": "Minuty przed zniknięciem",
    "menu:seconds_cooldown_for_mugging": "Sekundy odnowienia za napad",
    "menu:max_npc_following": "Maksymalna liczba NPC podążających jednocześnie",
    "menu:import_stages_from_heist": "Importuj etapy z napadu",
    "menu:doors_dialog:title": "Lista drzwi",
    "menu:doors_dialog:search_door": "Szukaj drzwi",
    "menu:customize_blip": "Dostosuj blip",
    "menu:choose_doors": "Wybierz drzwi",
    "menu:enable_npc_mugging": "Włącz rabunek NPC",
    "menu:apply_changes": "Zatwierdź zmiany",
    "menu:settings:enable_discord_logs": "Włącz logi Discord",
    "menu:settings:discord_webhooks": "Webhooki na Discordzie",
    "menu:settings:separated_webhooks": "Oddzielne webhooki",
    "menu:settings:main_webhook": "Główny webhook",
    "menu:global_timeout": "Globalny limit czasu (minuty)",
    "menu:global_timeout_description": "Po rozpoczęciu jednego napadu wszystkie inne napady zostaną wyłączone na te minuty",
    "menu:add_painting": "Dodaj obraz",
    "menu:painting": "Obraz",
    "menu:guards": "Ochroniarz",
    "menu:guards_list": "Lista ochroniarzy",
    "menu:add_guard": "Dodaj ochroniarza",
    "menu:add_guards": "Dodaj strażników",
    "menu:guard_model": "Model ochroniarza",
    "menu:guard_weapon": "Broń ochroniarza",
    "menu:headshot_will_oneshot": "Strzał w głowę będzie jednym strzałem",
    "menu:bruteforce": "Bruteforce",
    "menu:datacrack": "Datacrack",
    "menu:fingerprint": "Fingerprint",
    "menu:memory_game": "Memory game",
    "menu:not_allowed:you_are_not_allowed": "Nie możesz korzystać z tego menu",
    "menu:not_allowed:if_you_are_admin": "Jeśli jesteś administratorem serwera, musisz skopiować i wkleić następujący kod do pliku server.cfg"
}